resoto_plugin_aws/__init__.py
resoto_plugin_aws/aws_client.py
resoto_plugin_aws/collector.py
resoto_plugin_aws/configuration.py
resoto_plugin_aws/utils.py
resoto_plugin_aws/cmd/__init__.py
resoto_plugin_aws/resource/__init__.py
resoto_plugin_aws/resource/acm.py
resoto_plugin_aws/resource/apigateway.py
resoto_plugin_aws/resource/athena.py
resoto_plugin_aws/resource/autoscaling.py
resoto_plugin_aws/resource/base.py
resoto_plugin_aws/resource/cloudformation.py
resoto_plugin_aws/resource/cloudfront.py
resoto_plugin_aws/resource/cloudtrail.py
resoto_plugin_aws/resource/cloudwatch.py
resoto_plugin_aws/resource/cognito.py
resoto_plugin_aws/resource/config.py
resoto_plugin_aws/resource/dynamodb.py
resoto_plugin_aws/resource/ec2.py
resoto_plugin_aws/resource/ecr.py
resoto_plugin_aws/resource/ecs.py
resoto_plugin_aws/resource/efs.py
resoto_plugin_aws/resource/eks.py
resoto_plugin_aws/resource/elasticache.py
resoto_plugin_aws/resource/elasticbeanstalk.py
resoto_plugin_aws/resource/elb.py
resoto_plugin_aws/resource/elbv2.py
resoto_plugin_aws/resource/glacier.py
resoto_plugin_aws/resource/iam.py
resoto_plugin_aws/resource/kinesis.py
resoto_plugin_aws/resource/kms.py
resoto_plugin_aws/resource/lambda_.py
resoto_plugin_aws/resource/opensearch.py
resoto_plugin_aws/resource/pricing.py
resoto_plugin_aws/resource/rds.py
resoto_plugin_aws/resource/redshift.py
resoto_plugin_aws/resource/route53.py
resoto_plugin_aws/resource/s3.py
resoto_plugin_aws/resource/sagemaker.py
resoto_plugin_aws/resource/secretsmanager.py
resoto_plugin_aws/resource/service_quotas.py
resoto_plugin_aws/resource/sns.py
resoto_plugin_aws/resource/sqs.py
resoto_plugin_aws/resource/ssm.py
resoto_plugin_aws/resource/waf.py
test/__init__.py
test/aws_client_test.py
test/collector_test.py
test/configuration_test.py
test/graphbuilder_test.py
test/test_utils.py
test/resources/__init__.py
test/resources/acm_test.py
test/resources/apigateway_test.py
test/resources/athena_test.py
test/resources/autoscaling_test.py
resoto_plugin_aws-3.9.0.dist-info/METADATA
resoto_plugin_aws-3.9.0.dist-info/WHEEL
resoto_plugin_aws-3.9.0.dist-info/entry_points.txt
resoto_plugin_aws-3.9.0.dist-info/top_level.txt
resoto_plugin_aws-3.9.0.dist-info/RECORD
